AUTHORS.rst
CONTRIBUTING.rst
HISTORY.rst
LICENSE
MANIFEST.in
README.rst
setup.cfg
setup.py
docs/Makefile
docs/authors.rst
docs/conf.py
docs/contributing.rst
docs/history.rst
docs/index.rst
docs/installation.rst
docs/make.bat
docs/readme.rst
docs/riot_apy.apis.rst
docs/riot_apy.classes.rst
docs/riot_apy.rst
docs/usage.rst
docs/_build/html/_static/file.png
docs/_build/html/_static/minus.png
docs/_build/html/_static/plus.png
riot_apy/__init__.py
riot_apy/riot_apy.py
riot_apy.egg-info/PKG-INFO
riot_apy.egg-info/SOURCES.txt
riot_apy.egg-info/dependency_links.txt
riot_apy.egg-info/not-zip-safe
riot_apy.egg-info/requires.txt
riot_apy.egg-info/top_level.txt
riot_apy/apis/ChampionAPI.py
riot_apy/apis/ChampionMasteryAPI.py
riot_apy/apis/DataDragonAPI.py
riot_apy/apis/LeagueAPI.py
riot_apy/apis/MatchAPI.py
riot_apy/apis/SpectatorAPI.py
riot_apy/apis/SummonerAPI.py
riot_apy/apis/__init__.py
riot_apy/classes/ChampionClass.py
riot_apy/classes/ChampionMasteryClass.py
riot_apy/classes/DataDragonClass.py
riot_apy/classes/LeagueClass.py
riot_apy/classes/MatchClass.py
riot_apy/classes/SpectatorClass.py
riot_apy/classes/SummonerClass.py
riot_apy/classes/__init__.py