Metadata-Version: 1.2
Name: riot-apy
Version: 0.1.0
Summary: Riot API wrapper for Python
Home-page: https://github.com/mAxYoLo01/riot_apy
Author: Max Hirtz
Author-email: maxyolo01.ytb@gmail.com
License: MIT license
Download-URL: https://github.com/mAxYoLo01/Riot-APY/archive/0.1.0.tar.gz
Keywords: riot_apy
Platform: UNKNOWN
Classifier: Development Status :: 2 - Pre-Alpha
Classifier: Intended Audience :: Developers
Classifier: License :: OSI Approved :: MIT License
Classifier: Natural Language :: English
Classifier: Programming Language :: Python :: 3
Classifier: Programming Language :: Python :: 3.5
Classifier: Programming Language :: Python :: 3.6
Classifier: Programming Language :: Python :: 3.7
Classifier: Programming Language :: Python :: 3.8
Requires-Python: >=3.5
